{"indexed": {"date-parts": [[2020, 7, 31]], "date-time": "2020-07-31T22:03:56Z", "timestamp": 1596233036916}, "reference-count": 0, "publisher": "University of Minnesota Press", "isbn-type": [{"value": "9780816699544", "type": "print"}, {"value": "1452951489", "type": "electronic"}], "content-domain": {"domain": [], "crossmark-restriction": false}, "published-print": {"date-parts": [[2016, 5, 18]]}, "DOI": "10.5749/j.ctt1cn6thb.28", "type": "book-chapter", "created": {"date-parts": [[2020, 4, 23]], "date-time": "2020-04-23T20:37:07Z", "timestamp": 1587674227000}, "page": "289-307", "source": "Crossref", "is-referenced-by-count": 1, "title": ["The Differences between Digital Humanities and Digital History"], "prefix": "10.5749", "author": [{"given": "STEPHEN", "family": "ROBERTSON", "sequence": "first", "affiliation": []}], "member": "3779", "container-title": ["Debates in the Digital Humanities 2016"], "deposited": {"date-parts": [[2020, 4, 23]], "date-time": "2020-04-23T20:37:32Z", "timestamp": 1587674252000}, "score": 87.92878, "issued": {"date-parts": [[2016, 5, 18]]}, "ISBN": ["9781452951485", "1452951489", "9780816699544"], "references-count": 0, "URL": "http://dx.doi.org/10.5749/j.ctt1cn6thb.28"}