{"indexed": {"date-parts": [[2020, 4, 13]], "date-time": "2020-04-13T20:22:03Z", "timestamp": 1586809323229}, "reference-count": 0, "publisher": "Wiley", "issue": "4", "license": [{"URL": "http://doi.wiley.com/10.1002/tdm_license_1.1", "start": {"date-parts": [[2015, 9, 1]], "date-time": "2015-09-01T00:00:00Z", "timestamp": 1441065600000}, "delay-in-days": 2344, "content-version": "tdm"}], "content-domain": {"domain": [], "crossmark-restriction": false}, "short-container-title": [], "published-print": {"date-parts": [[2009, 4]]}, "DOI": "10.1111/j.1556-3502.2009.50404.x", "type": "journal-article", "created": {"date-parts": [[2009, 3, 30]], "date-time": "2009-03-30T15:51:42Z", "timestamp": 1238428302000}, "page": "4-5", "source": "Crossref", "is-referenced-by-count": 16, "title": ["Access and Accountability: The Ecology of Information Sharing in the Digital Age"], "prefix": "10.1111", "volume": "50", "author": [{"given": "Kimberly", "family": "Christen", "sequence": "first", "affiliation": []}], "member": "311", "container-title": ["Anthropology News"], "original-title": [], "language": "en", "link": [{"URL": "https://api.wiley.com/onlinelibrary/tdm/v1/articles/10.1111%2Fj.1556-3502.2009.50404.x", "content-type": "unspecified", "content-version": "vor", "intended-application": "text-mining"}], "deposited": {"date-parts": [[2017, 3, 30]], "date-time": "2017-03-30T15:51:07Z", "timestamp": 1490889067000}, "score": 1.0, "subtitle": [], "short-title": [], "issued": {"date-parts": [[2009, 4]]}, "references-count": 0, "journal-issue": {"published-print": {"date-parts": [[2009, 4]]}, "issue": "4"}, "URL": "http://dx.doi.org/10.1111/j.1556-3502.2009.50404.x", "relation": {}, "ISSN": ["1541-6151", "1556-3502"], "issn-type": [{"value": "1541-6151", "type": "print"}, {"value": "1556-3502", "type": "electronic"}]}