{"indexed": {"date-parts": [[2020, 6, 12]], "date-time": "2020-06-12T04:11:39Z", "timestamp": 1591935099663}, "reference-count": 80, "publisher": "Cambridge University Press (CUP)", "issue": "4", "license": [{"URL": "http://doi.wiley.com/10.1002/tdm_license_1.1", "start": {"date-parts": [[2015, 9, 1]], "date-time": "2015-09-01T00:00:00Z", "timestamp": 1441065600000}, "delay-in-days": 3105, "content-version": "tdm"}], "content-domain": {"domain": [], "crossmark-restriction": false}, "DOI": "10.1111/j.1747-4469.2005.tb01145.x", "type": "journal-article", "created": {"date-parts": [[2010, 9, 17]], "date-time": "2010-09-17T12:45:03Z", "timestamp": 1284727503000}, "page": "763-782", "source": "Crossref", "is-referenced-by-count": 1, "title": ["Lessons from the Globalization of Consumer Bankruptcy"], "prefix": "10.1017", "volume": "30", "author": [{"given": "Charles J.", "family": "Tabb", "sequence": "first", "affiliation": []}], "member": "56", "published-online": {"date-parts": [[2007, 3, 2]]}, "reference": [{"key": "10.1111/j.1747-4469.2005.tb01145.x-BIB1|cit1", "first-page": "521", "article-title": "Festschrift for Ruth Ann and James Wilson: A Review of Consumer Bankruptcy in Global Perspective", "volume": "12", "author": "Aaron", "year": "2004", "journal-title": "American Bankruptcy Institute Law Review"}, {"key": "10.1111/j.1747-4469.2005.tb01145.x-BIB2|cit2", "doi-asserted-by": "crossref", "first-page": "585", "DOI": "10.1086/468086", "article-title": "Regulating Consumer Bankruptcy: A Theoretical Inquiry", "volume": "29", "author": "Adler", "year": "2000", "journal-title": "Journal of Legal Studies"}, {"key": "10.1111/j.1747-4469.2005.tb01145.x-BIB3|cit3", "first-page": "249", "article-title": "Credit Card Defaults, Credit Card Profits, and Bankruptcy", "volume": "71", "author": "Ausubel", "year": "1997", "journal-title": "American Bankruptcy Law Journal"}, {"key": "10.1111/j.1747-4469.2005.tb01145.x-BIB4|cit4", "unstructured": "Berry , Ruth E. Sue L. T. McGregor 1999 Counselling Consumer Debtors under Canada's Bankruptcy and Insolvency Act 369 85"}, {"key": "10.1111/j.1747-4469.2005.tb01145.x-BIB5|cit5", "unstructured": "Booth , Charles 2003 Current Trends in Consumer Insolvency in Hong Kong Niemi-Kiesil\u00e4inen, Ramsay, and Whitford 2003a 187 202"}, {"key": "10.1111/j.1747-4469.2005.tb01145.x-BIB6|cit6", "doi-asserted-by": "crossref", "first-page": "69", "DOI": "10.2307/3311830", "article-title": "Limited, Conditional, and Suspended Discharges in Anglo-American Bankruptcy Proceedings", "volume": "131", "author": "Boshkoff", "year": "1982", "journal-title": "University of Pennsylvania Law Review"}, {"key": "10.1111/j.1747-4469.2005.tb01145.x-BIB7|cit7", "first-page": "501", "article-title": "Lawyers and Consumer Bankruptcy: One Code, Many Cultures", "volume": "67", "author": "Braucher", "year": "1993", "journal-title": "American Bankruptcy Law Journal"}, {"key": "10.1111/j.1747-4469.2005.tb01145.x-BIB8|cit8", "unstructured": "Braucher , Jean. 1999 Options in Consumer Bankruptcy: An American Perspective 155 70"}, {"key": "10.1111/j.1747-4469.2005.tb01145.x-BIB9|cit9", "unstructured": "Braucher , Jean. 2003 Debtor Education in Bankruptcy: The Perspective of Interest Analysis Niemi-Kiesil\u00e4inen, Ramsay, and Whitford 2003a 319 42"}, {"key": "10.1111/j.1747-4469.2005.tb01145.x-BIB10|cit10", "author": "Coleman", "first-page": "1999", "year": "1974", "volume-title": "Debtors and Creditors in America: Insolvency, Imprisonment for Debt, and Bankruptcy, 1607-1900"}, {"key": "10.1111/j.1747-4469.2005.tb01145.x-BIB11|cit11", "first-page": "27", "article-title": "Taking the New Consumer Bankruptcy Model for a Test Drive: Means-Testing Real Chapter 7 Debtors", "volume": "7", "author": "Culhane", "year": "1999", "journal-title": "American Bankruptcy Institute Law Review"}, {"key": "10.1111/j.1747-4469.2005.tb01145.x-BIB12|cit12", "unstructured": "Curnock , Carol Ann. 1999 Insolvency Counselling-Innovation Based on the Fourteenth Century 387 407"}, {"key": "10.1111/j.1747-4469.2005.tb01145.x-BIB13|cit13", "unstructured": "Defoe , Daniel 1697 Of Bankrupts 1 3"}, {"key": "10.1111/j.1747-4469.2005.tb01145.x-BIB14|cit14", "first-page": "81", "article-title": "Global Trends in Personal Bankruptcy", "volume": "76", "author": "Efrat", "year": "2002", "journal-title": "American Bankruptcy Law Journal"}, {"key": "10.1111/j.1747-4469.2005.tb01145.x-BIB15|cit15", "unstructured": "Efrat , Rafael 2003 The Political Economy of Personal Bankruptcy in Israel Niemi-Kiesil\u00e4inen, Ramsay, and Whitford 2003a 167 85"}, {"key": "10.1111/j.1747-4469.2005.tb01145.x-BIB16|cit16", "first-page": "351", "article-title": "Legal Culture and Bankruptcy: A Comparative Perspective", "volume": "20", "author": "Efrat", "year": "2004", "journal-title": "Emory Bankruptcy Developments Journal"}, {"key": "10.1111/j.1747-4469.2005.tb01145.x-BIB17|cit17", "first-page": "953", "article-title": "Bankruptcy Law in Perspective", "volume": "28", "author": "Eisenberg", "year": "1981", "journal-title": "UCLA Law Review"}, {"key": "10.1111/j.1747-4469.2005.tb01145.x-BIB18|cit18", "doi-asserted-by": "crossref", "first-page": "169", "DOI": "10.1111/j.1468-2230.2005.533_6.x", "article-title": "Review of Niemi-Kiesil\u00e4inen et al., Consumer Bankruptcy in Global Perspective, and Ziegel, Comparative Consumer Insolvency Regimes: A Canadian Perspective", "volume": "68", "author": "Franken", "year": "2005", "journal-title": "Modern Law Review"}, {"key": "10.1111/j.1747-4469.2005.tb01145.x-BIB19|cit19", "author": "Freyer", "year": "2005", "volume-title": "Debt Failure and the Development of American Capitalism: An Essay on Bruce Mann's Pro-debtor Republic"}, {"key": "10.1111/j.1747-4469.2005.tb01145.x-BIB20|cit20", "unstructured": "Graver , Hans Peter. 1997 Consumer Bankruptcy: A Right or a Privilege? The Role of the Courts in Establishing Moral Standards of Economic Conduct Niemi-Kiesil\u00e4inen and Ramsay 161 77", "DOI": "10.1023/A:1006882617499", "doi-asserted-by": "crossref"}, {"key": "10.1111/j.1747-4469.2005.tb01145.x-BIB21|cit21", "unstructured": "Gross , Karen 2003 Establishing Financial Literacy Programmes for Consumer Debtors: Complex Issues on the Platter Niemi-Kiesil\u00e4inen, Ramsay, and Whitford 2003a 343 60"}, {"key": "10.1111/j.1747-4469.2005.tb01145.x-BIB22|cit22", "unstructured": "Heath , Paul, Q.C. 1999 Consumer Bankruptcies: A New Zealand Perspective Ziegel 1999a 427 47", "DOI": "10.1080/00480169.1999.36147", "doi-asserted-by": "crossref"}, {"key": "10.1111/j.1747-4469.2005.tb01145.x-BIB23|cit23", "unstructured": "Honsberger , John D., Q.C. 1999 Philosophy and Design of Modem Fresh Start Policies: The Evolution of Canada's Legislative Policy Ziegel 1999a 171 88"}, {"key": "10.1111/j.1747-4469.2005.tb01145.x-BIB24|cit24", "unstructured": "House of Representatives 1977"}, {"key": "10.1111/j.1747-4469.2005.tb01145.x-BIB25|cit25", "unstructured": "Huls , Nick 1992 American Influences on European Consumer Bankruptcy Law Journal of Consumer Policy 15", "DOI": "10.1007/BF01352132", "doi-asserted-by": "crossref"}, {"key": "10.1111/j.1747-4469.2005.tb01145.x-BIB26|cit26", "unstructured": "Huls, Nick , Nadja Jungmann Bert Niemeijer 2003 Can Voluntary Debt Settlement and Consumer Bankruptcy Coexist? The Development of Dutch Insolvency Law Niemi-Kiesil\u00e4inen, Ramsay, and Whitford 2003a 303 18"}, {"key": "10.1111/j.1747-4469.2005.tb01145.x-BIB27|cit27", "doi-asserted-by": "crossref", "first-page": "1393", "DOI": "10.2307/1340952", "article-title": "The Fresh-Start Policy in Bankruptcy", "volume": "98", "author": "Jackson", "year": "1985", "journal-title": "Harvard Law Review"}, {"key": "10.1111/j.1747-4469.2005.tb01145.x-BIB28|cit28", "unstructured": "Jacoby , Melissa B. 2003 Generosity versus Accessibility: Bankruptcy, Consumer Credit, and Health Care Finance in the U.S. Niemi-Kiesil\u00e4inen, Ramsay, and Whitford 2003a 283 300"}, {"key": "10.1111/j.1747-4469.2005.tb01145.x-BIB29|cit29", "unstructured": "Jones , Edith H. James I. Shepherd 1997 Additional Dissent to Recommendations for Reform of Consumer Bankruptcy Law http://govinfo.library.unt.edu/nbrc/reportcont.html"}, {"key": "10.1111/j.1747-4469.2005.tb01145.x-BIB30|cit30", "first-page": "177", "article-title": "It's Time for Means-Testing", "volume": "1999", "author": "Jones", "year": "1999", "journal-title": "BYU Law Review"}, {"key": "10.1111/j.1747-4469.2005.tb01145.x-BIB31|cit31", "first-page": "257", "article-title": "The Innovative German Approach to Consumer Debt Relief: Revolutionary Changes in German Law, and Surprising Lessons for the U.S", "volume": "24", "author": "Kilborn", "year": "2004", "journal-title": "Northwestern Journal of International Law and Business"}, {"key": "10.1111/j.1747-4469.2005.tb01145.x-BIB32|cit32", "first-page": "619", "article-title": "La Responsabilisation de L'Economie: What the United States Can Learn from the New French Law on Consumer Overindebtedness", "volume": "26", "author": "Kilborn", "year": "2005a", "journal-title": "Michigan Journal of International Law"}, {"key": "10.1111/j.1747-4469.2005.tb01145.x-BIB33|cit33", "unstructured": "Kilborn , Jason J. 2005b Continuity, Change, and Innovation in Emerging Consumer Bankruptcy Systems: Belgium and Luxembourg", "DOI": "10.2139/ssrn.690802", "doi-asserted-by": "crossref"}, {"key": "10.1111/j.1747-4469.2005.tb01145.x-BIB34|cit34", "unstructured": "Kilborn , Jason J. 2005c Behavioral Economics, Overindebtedness, and Comparative Consumer Bankruptcy: Searching for Causes and Evaluating Solutions with the author", "DOI": "10.2139/ssrn.690826", "doi-asserted-by": "crossref"}, {"key": "10.1111/j.1747-4469.2005.tb01145.x-BIB35|cit35", "unstructured": "Lawless , Robert M. 2001 The Relationship between Nonbusiness Bankruptcy Filings and Various Measures of Consumer Debt 515 17", "DOI": "10.2139/ssrn.934798", "doi-asserted-by": "crossref"}, {"key": "10.1111/j.1747-4469.2005.tb01145.x-BIB36|cit36", "unstructured": "Lopes , Jos\u00e9 Reinaldo de Lima 2003 Consumer Bankruptcy and Over-indebtedness in Brazil Niemi-Kiesil\u00e4inen, Ramsay, and Whitford 2003a 85 103"}, {"key": "10.1111/j.1747-4469.2005.tb01145.x-BIB37|cit37", "first-page": "1498", "article-title": "Legal Culture, Legal Strategy, and the Law in Lawyers' Heads", "volume": "30", "author": "LoPucki", "year": "1996", "journal-title": "Northwestern University Law Review"}, {"key": "10.1111/j.1747-4469.2005.tb01145.x-BIB38|cit38", "author": "Mann", "year": "2002", "volume-title": "Republic of Debtors: Bankruptcy in the Age of American Independence"}, {"key": "10.1111/j.1747-4469.2005.tb01145.x-BIB39|cit39", "unstructured": "Marques , Maria Manuel Leit\u00e3o Catarina Frade 2003 Searching for an Over-indebtedness Regulatory System for Portugal and the European Union Niemi-Kiesil\u00e4inen, Ramsay, and Whitford 2003a 121 40"}, {"key": "10.1111/j.1747-4469.2005.tb01145.x-BIB40|cit40", "first-page": "367", "article-title": "Common-Law Bankruptcy Systems: Similarities and Differences", "volume": "11", "author": "Martin", "year": "2003", "journal-title": "American Bankruptcy Institute Law Review"}, {"key": "10.1111/j.1747-4469.2005.tb01145.x-BIB41|cit41", "first-page": "1", "article-title": "The Role of History and Culture in Developing Bankruptcy and Insolvency Systems: The Perils of Legal Transplantation", "volume": "28", "author": "Martin", "year": "2005", "journal-title": "Boston College International and Comparative Law Review"}, {"key": "10.1111/j.1747-4469.2005.tb01145.x-BIB42|cit42", "unstructured": "Mason , Rosalind 1999 Consumer Bankruptcies: An Australian Perspective 449 72"}, {"key": "10.1111/j.1747-4469.2005.tb01145.x-BIB43|cit43", "unstructured": "Mason , Rosalind John Duns 2003 Developments in Consumer Bankruptcy in Australia Niemi-Kiesil\u00e4inen, Ramsay, and Whitford 2003a 227 46"}, {"key": "10.1111/j.1747-4469.2005.tb01145.x-BIB44|cit44", "first-page": "163", "article-title": "Discharge: The Most Important Development in Bankruptcy History", "volume": "70", "author": "McCoid", "year": "1996", "journal-title": "American Bankruptcy Law Journal"}, {"key": "10.1111/j.1747-4469.2005.tb01145.x-BIB45|cit45", "year": "1997", "volume-title": "National Bankruptcy Review Commission Final Report"}, {"key": "10.1111/j.1747-4469.2005.tb01145.x-BIB46|cit46", "unstructured": "Niemi-Kiesil\u00e4inen , Johanna 1997 Changing Directions in Consumer Bankruptcy Law and Practice in Europe and USA Niemi-Kiesil\u00e4inen and Ramsay 1997 133 42", "DOI": "10.1023/A:1006829100661", "doi-asserted-by": "crossref"}, {"key": "10.1111/j.1747-4469.2005.tb01145.x-BIB47|cit47", "unstructured": "Niemi-Kiesil\u00e4inen , Johanna 1999 Consumer Bankruptcy in Comparison: Do We Cure a Market Failure or a Social Problem 473 503"}, {"key": "10.1111/j.1747-4469.2005.tb01145.x-BIB48|cit48", "unstructured": "Niemi-Kiesil\u00e4inen , Johanna 2003 Collective or Individual? Constructions of Debtors and Creditors in Consumer Bankruptcy Niemi-Kiesil\u00e4inen, Ramsay, and Whitford 2003a 41 60"}, {"key": "10.1111/j.1747-4469.2005.tb01145.x-BIB49|cit49", "doi-asserted-by": "crossref", "first-page": "133", "DOI": "10.1023/A:1006829100661", "article-title": "Special Issue: Changing Directions in Consumer Bankruptcy Law and Practice in Europe and North America", "volume": "20", "author": "Niemi-Kiesil\u00e4inen", "year": "1997", "journal-title": "Journal of Consumer Policy"}, {"key": "10.1111/j.1747-4469.2005.tb01145.x-BIB50|cit50", "year": "2003a", "volume-title": "Consumer Bankruptcy in Global Perspective"}, {"key": "10.1111/j.1747-4469.2005.tb01145.x-BIB51|cit51", "unstructured": "Niemi-Kiesil\u00e4inen , Johanna 2003b Introduction Niemi-Kiesil\u00e4inen, Ramsay, and Whitford 2003a 1 14"}, {"key": "10.1111/j.1747-4469.2005.tb01145.x-BIB52|cit52", "unstructured": "Ramsay , Iain 1997 Models of Consumer Bankruptcy: Implications for Research and Policy Niemi-Kiesil\u00e4inen and Ramsay 1997 269 87", "DOI": "10.1023/A:1006854416706", "doi-asserted-by": "crossref"}, {"key": "10.1111/j.1747-4469.2005.tb01145.x-BIB53|cit53", "unstructured": "Ramsay , Iain 1999 Individual Bankruptcy: Preliminary Findings of a Socio-Legal Analysis 15 82"}, {"key": "10.1111/j.1747-4469.2005.tb01145.x-BIB54|cit54", "unstructured": "Ramsay , Iain 2003a Bankruptcy in Transition: The Case of England and Wales-the Neoliberal Cuckoo in the European Bankruptcy Nest Niemi-Kiesil\u00e4inen, Ramsay, and Whitford 2003a 205 25"}, {"key": "10.1111/j.1747-4469.2005.tb01145.x-BIB55|cit55", "unstructured": "Ramsay , Iain 2003b Consumer Credit Society and Consumer Bankruptcy: Reflections on Credit Cards and Bankruptcy in the Informational Economy Niemi-Kiesil\u00e4inen, Ramsay, and Whitford 2003a 17 39"}, {"key": "10.1111/j.1747-4469.2005.tb01145.x-BIB56|cit56", "unstructured": "Reifner , Udo 2003 \u201cThou shalt pay thy debts\u201d: Personal Bankruptcy Law and Inclusive Contract Law Niemi-Kiesil\u00e4inen, Ramsay, and Whitford 2003a 143 66"}, {"key": "10.1111/j.1747-4469.2005.tb01145.x-BIB57|cit57", "doi-asserted-by": "crossref", "first-page": "671", "DOI": "10.1093/ajcl/50.4.671", "article-title": "The Progress and Failure of Comparative Law in the Second Half of the Twentieth Century", "volume": "50", "author": "Riemann", "year": "2002", "journal-title": "American Journal of Comparative Law"}, {"key": "10.1111/j.1747-4469.2005.tb01145.x-BIB58|cit58", "unstructured": "Schwartz , Saul 1999 The Empirical Dimensions of Consumer Bankruptcy: Results from a Survey of Canadian Bankrupts 83 125"}, {"key": "10.1111/j.1747-4469.2005.tb01145.x-BIB59|cit59", "unstructured": "Schwartz , Saul 2003 Personal Bankruptcy Law: A Behavioural Perspective Niemi-Kiesil\u00e4inen, Ramsay, and Whitford 2003a 61 82"}, {"key": "10.1111/j.1747-4469.2005.tb01145.x-BIB60|cit60", "author": "Stencel", "year": "2004", "volume-title": "The Persistent Stigma of Bankruptcy and Its Effect on Debtors"}, {"key": "10.1111/j.1747-4469.2005.tb01145.x-BIB61|cit61", "unstructured": "Sullivan , Teresa A. Elizabeth Warren Jay Lawrence Westbrook 1997 Consumer Bankruptcy in the United States: A Study of Alleged Abuse and of Local Legal Culture Niemi-Kiesil\u00e4inen and Ramsay 1997 223 68", "DOI": "10.1023/A:1006826006249", "doi-asserted-by": "crossref"}, {"key": "10.1111/j.1747-4469.2005.tb01145.x-BIB62|cit62", "author": "Sullivan", "year": "2000", "volume-title": "The Fragile Middle Class: Americans in Debt"}, {"key": "10.1111/j.1747-4469.2005.tb01145.x-BIB63|cit63", "first-page": "325", "article-title": "The Historical Evolution of the Bankruptcy Discharge", "volume": "65", "author": "Tabb", "year": "1991", "journal-title": "American Bankruptcy Law journal"}, {"key": "10.1111/j.1747-4469.2005.tb01145.x-BIB64|cit64", "first-page": "5", "article-title": "The History of the Bankruptcy Laws in the United States", "volume": "3", "author": "Tabb", "year": "1995", "journal-title": "American Bankruptcy Institute Law Review"}, {"key": "10.1111/j.1747-4469.2005.tb01145.x-BIB65|cit65", "author": "Tabb", "year": "1997", "volume-title": "The Law of Bankruptcy"}, {"key": "10.1111/j.1747-4469.2005.tb01145.x-BIB66|cit66", "first-page": "343", "article-title": "A Century of Regress or Progress?: A Political History of Bankruptcy Legislation in 1898 and 1998", "volume": "15", "author": "Tabb", "year": "1999", "journal-title": "Bankruptcy Developments Journal"}, {"key": "10.1111/j.1747-4469.2005.tb01145.x-BIB67|cit67", "author": "Tabb", "year": "2002", "volume-title": "Bankruptcy Anthology"}, {"key": "10.1111/j.1747-4469.2005.tb01145.x-BIB68|cit68", "unstructured": "Tabb , Charles Jordan 2003 The Death of Consumer Bankruptcy in the United States Ricketts and Telfer 2003 264 99", "DOI": "10.1017/CBO9780511494833.013", "doi-asserted-by": "crossref"}, {"key": "10.1111/j.1747-4469.2005.tb01145.x-BIB69|cit69", "first-page": "259", "article-title": "Of Contractarians and Bankruptcy Reform: A Skeptical View", "volume": "12", "author": "Tabb", "year": "2004", "journal-title": "American Bankruptcy Institute Law Review"}, {"key": "10.1111/j.1747-4469.2005.tb01145.x-BIB70|cit70", "unstructured": "Telfer , Thomas G. W. 2003 Access to the Discharge in Canadian Bankruptcy Law and the New Role of Surplus Income: A Historical Perspective Ricketts and Telfer 2003 231 63", "DOI": "10.1017/CBO9780511494833.012", "doi-asserted-by": "crossref"}, {"key": "10.1111/j.1747-4469.2005.tb01145.x-BIB71|cit71", "author": "Tsai", "year": "2004", "volume-title": "Comparison of the Bankruptcy Law between Taiwan and the United States-Explanations for Taiwanese Reluctance to Access the Bankruptcy System"}, {"key": "10.1111/j.1747-4469.2005.tb01145.x-BIB72|cit72", "doi-asserted-by": "crossref", "first-page": "65", "DOI": "10.1080/14735970.2005.11419930", "article-title": "Personal Insolvency Law after the Enterprise Act: An Appraisal", "volume": "5", "author": "Walters", "year": "2005", "journal-title": "Journal of Corporate Law Studies"}, {"key": "10.1111/j.1747-4469.2005.tb01145.x-BIB73|cit73", "author": "Warren", "year": "1935", "volume-title": "Bankruptcy in United States History", "DOI": "10.4159/harvard.9780674436442", "doi-asserted-by": "crossref"}, {"key": "10.1111/j.1747-4469.2005.tb01145.x-BIB74|cit74", "unstructured": "Warren , Elizabeth 1999 The Changing Politics of American Bankruptcy Reform"}, {"key": "10.1111/j.1747-4469.2005.tb01145.x-BIB75|cit75", "unstructured": "Zhang , Xian-chu 2003 Development of Consumer Credit in China and Concerns about the Underlying Legal Infrastructure Niemi-Kiesil\u00e4inen, Ramsay, and Whitford 2003a 105 20"}, {"key": "10.1111/j.1747-4469.2005.tb01145.x-BIB76|cit76", "unstructured": "Ziegel , Jacob S. 1997 Canadian Perspectives on the Challenges of Consumer Bankruptcies Niemi-Kiesil\u00e4inen and Ramsay 1997 199 211", "DOI": "10.1023/A:1006897824633", "doi-asserted-by": "crossref"}, {"key": "10.1111/j.1747-4469.2005.tb01145.x-BIB77|cit77", "first-page": "1", "article-title": "Symposium: Consumer Bankruptcies in a Comparative Context", "volume": "37", "author": "Ziegel", "year": "1999a", "journal-title": "Osgoode Hall Law Journal"}, {"key": "10.1111/j.1747-4469.2005.tb01145.x-BIB78|cit78", "unstructured": "Ziegel , Jacob S. 1999b Introduction to the Symposium on Consumer Bankruptcies 1 13"}, {"key": "10.1111/j.1747-4469.2005.tb01145.x-BIB79|cit79", "unstructured": "Ziegel , Jacob S. 1999c The Philosophy and Design of Contemporary Consumer Bankruptcy Systems: A Canada-United States Comparison 205 57"}, {"key": "10.1111/j.1747-4469.2005.tb01145.x-BIB80|cit80", "author": "Ziegel", "year": "2003", "volume-title": "Comparative Consumer Insolvency Regimes: A Canadian Perspective"}], "container-title": ["Law & Social Inquiry"], "language": "en", "link": [{"URL": "https://api.wiley.com/onlinelibrary/tdm/v1/articles/10.1111%2Fj.1747-4469.2005.tb01145.x", "content-type": "unspecified", "content-version": "vor", "intended-application": "text-mining"}], "deposited": {"date-parts": [[2020, 6, 11]], "date-time": "2020-06-11T21:33:06Z", "timestamp": 1591911186000}, "score": 25.924902, "issued": {"date-parts": [[2007, 3, 2]]}, "references-count": 80, "journal-issue": {"issue": "4"}, "URL": "http://dx.doi.org/10.1111/j.1747-4469.2005.tb01145.x", "relation": {"cites": []}, "ISSN": ["0897-6546"], "issn-type": [{"value": "0897-6546", "type": "print"}], "subject": ["General Social Sciences", "Law"]}