{"indexed": {"date-parts": [[2020, 7, 29]], "date-time": "2020-07-29T22:04:42Z", "timestamp": 1596060282722}, "reference-count": 0, "publisher": "Edward Elgar Publishing", "isbn-type": [{"value": "9780857933522", "type": "electronic"}], "content-domain": {"domain": [], "crossmark-restriction": false}, "published-print": {"date-parts": [[2011]]}, "DOI": "10.4337/9780857933522", "type": "monograph", "created": {"date-parts": [[2013, 9, 17]], "date-time": "2013-09-17T09:14:46Z", "timestamp": 1379409286000}, "source": "Crossref", "is-referenced-by-count": 10, "title": ["Copyright, Communication and Culture"], "prefix": "10.4337", "author": [{"given": "Carys", "family": "Craig", "sequence": "first", "affiliation": []}], "member": "2918", "deposited": {"date-parts": [[2015, 3, 12]], "date-time": "2015-03-12T14:11:58Z", "timestamp": 1426169518000}, "score": 65.645706, "issued": {"date-parts": [[2011]]}, "ISBN": ["9780857933522"], "references-count": 0, "URL": "http://dx.doi.org/10.4337/9780857933522"}