{"indexed": {"date-parts": [[2020, 1, 22]], "date-time": "2020-01-22T09:23:30Z", "timestamp": 1579685010365}, "publisher-location": "London", "reference-count": 28, "publisher": "Palgrave Macmillan UK", "isbn-type": [{"value": "9781349439225", "type": "print"}, {"value": "9781137026521", "type": "electronic"}], "license": [{"URL": "http://www.springer.com/tdm", "start": {"date-parts": [[2013, 1, 1]], "date-time": "2013-01-01T00:00:00Z", "timestamp": 1356998400000}, "delay-in-days": 0, "content-version": "unspecified"}], "content-domain": {"domain": [], "crossmark-restriction": false}, "published-print": {"date-parts": [[2013]]}, "DOI": "10.1057/9781137026521_8", "type": "book-chapter", "created": {"date-parts": [[2016, 5, 21]], "date-time": "2016-05-21T09:50:18Z", "timestamp": 1463824218000}, "page": "145-165", "source": "Crossref", "is-referenced-by-count": 7, "title": ["On Knowing Your Own Beliefs: A Representationalist Account"], "prefix": "10.1057", "author": [{"given": "Peter", "family": "Carruthers", "sequence": "first", "affiliation": []}], "member": "297", "reference": [{"key": "8_CR1", "author": "B Baars", "year": "1988", "unstructured": "Baars, B. 1988, A Cognitive Theory of Consciousness, New York: Cambridge University Press.", "volume-title": "A Cognitive Theory of Consciousness"}, {"key": "8_CR2", "author": "A Baddeley", "year": "2006", "unstructured": "Baddeley, A. 2006, Working Memory, Thought, and Action, New York: Oxford University Press.", "volume-title": "Working Memory, Thought, and Action"}, {"key": "8_CR3", "author": "N Block", "year": "1986", "unstructured": "Block, N. 1986, \u201cAn Advertisement for a Semantics for Psychology\u201d, in French, P., Euhling, T., and Wettstein, H. (eds), Midwest Studies in Philosophy: 10: Studies in the Philosophy of Mind, Minneapolis, MN: University of Minnesota Press.", "volume-title": "Midwest Studies in Philosophy: 10: Studies in the Philosophy of Mind"}, {"key": "8_CR4", "author": "M Bratman", "year": "1987", "unstructured": "Bratman, M. 1987, Intentions, Plans, and Practical Reason, Cambridge, MA.: Harvard University Press.", "volume-title": "Intentions, Plans, and Practical Reason"}, {"key": "8_CR5", "author": "M Bratman", "year": "1999", "unstructured": "\u2014. 1999, Faces of Intention, New York: Cambridge University Press.", "volume-title": "Faces of Intention", "DOI": "10.1017/CBO9780511625190", "doi-asserted-by": "publisher"}, {"key": "8_CR6", "author": "P Carruthers", "year": "2011", "unstructured": "Carruthers, P. 2011, The Opacity of Mind, New York: Oxford University Press.", "volume-title": "The Opacity of Mind"}, {"key": "8_CR7", "doi-asserted-by": "publisher", "first-page": "141", "DOI": "10.1111/mila.12014", "volume": "38", "author": "P Carruthers", "year": "2013", "unstructured": "\u2014. 2013, \u201cMindreading in Infancy\u201d, Mind & Language, 38, 141\u2013172.", "journal-title": "Mind & Language"}, {"key": "8_CR8", "author": "L Cohen", "year": "1992", "unstructured": "Cohen, L. 1992, An Essay on Belief and Acceptance. New York: Oxford University Press.", "volume-title": "An Essay on Belief and Acceptance"}, {"key": "8_CR9", "author": "A Damasio", "year": "1994", "unstructured": "Damasio, A. 1994, Descartes\u2019 Error, London: Papermac.", "volume-title": "Descartes\u2019 Error"}, {"key": "8_CR10", "author": "D Dennett", "year": "1978", "unstructured": "Dennett, D. 1978, Brainstorms, Brighton: Harvester Press.", "volume-title": "Brainstorms"}, {"key": "8_CR11", "doi-asserted-by": "publisher", "first-page": "255", "DOI": "10.1146/annurev.psych.59.103006.093629", "volume": "59", "author": "J Evans", "year": "2008", "unstructured": "Evans, J. 2008, \u201cDual-processing Accounts of Reasoning, Judgment, and Social Cognition\u201d, Annual Review of Psychology 59, 255\u2013278.", "journal-title": "Annual Review of Psychology"}, {"key": "8_CR12", "author": "J Evans", "year": "2010", "unstructured": "\u2014. 2010, Thinking Twice, New York: Oxford University Press.", "volume-title": "Thinking Twice"}, {"key": "8_CR13", "author": "J Evans", "year": "1996", "unstructured": "Evans, J., and Over, D. 1996, Rationality and Reasoning, Hove, Sussex: Psychology Press.", "volume-title": "Rationality and Reasoning"}, {"key": "8_CR14", "author": "K Frankish", "year": "2004", "unstructured": "Frankish, K. 2004, Mind and Supermind, New York: Cambridge University Press.", "volume-title": "Mind and Supermind", "DOI": "10.1017/CBO9780511487507", "doi-asserted-by": "publisher"}, {"key": "8_CR15", "author": "K Frankish", "year": "2009", "unstructured": "\u2014. 2009, \u201cSystems and Levels\u201d, in Evans, J. and Frankish, K. (eds), In Two Minds, New York: Oxford University Press.", "volume-title": "In Two Minds"}, {"key": "8_CR16", "doi-asserted-by": "publisher", "first-page": "41", "DOI": "10.1007/s11299-011-0094-5", "volume": "11", "author": "K Frankish", "year": "2012", "unstructured": "\u2014. (2012). \u201cDual Systems and Dual Attitudes\u201d, Mind & Society 11, 41\u201351.", "journal-title": "Mind & Society"}, {"key": "8_CR17", "doi-asserted-by": "publisher", "first-page": "193", "DOI": "10.1146/annurev.psych.59.103006.093615", "volume": "59", "author": "J Jonides", "year": "2008", "unstructured": "Jonides, J., Lewis, R., Nee, D., Lustig, C., Berman, M., and Moore, K. 2008, \u201cThe Mind and Brain of Short-term Memory\u201d, Annual Review of Psychology 59, 193\u2013224.", "journal-title": "Annual Review of Psychology"}, {"key": "8_CR18", "author": "D Kahneman", "year": "2011", "unstructured": "Kahneman, D. 2011, Thinking, Fast and Slow, New York: Farrar, Straus, and Giroux.", "volume-title": "Thinking, Fast and Slow"}, {"key": "8_CR19", "author": "R Millikan", "year": "1984", "unstructured": "Millikan, R. 1984, Language, Thought, and Other Biological Categories, Cambridge, MA: MIT Press.", "volume-title": "Language, Thought, and Other Biological Categories"}, {"key": "8_CR20", "author": "S Nichols", "year": "2003", "unstructured": "Nichols, S. and Stich, S. 2003, Mindreading, New York: Oxford University Press.", "volume-title": "Mindreading", "DOI": "10.1093/0198236107.001.0001", "doi-asserted-by": "publisher"}, {"key": "8_CR21", "author": "W Ramsey", "year": "1990", "unstructured": "Ramsey, W., Stich, S., and Garon, J. 1990, \u201cConnectionism, Eliminativism, and the Future of Folk Psychology\u201d, in Tomberlin, J. (ed.), Philosophical Perspectives 4: Action Theory and Philosophy of Mind, Ridgeview, CA.: Ridgeview Publishing.", "volume-title": "Philosophical Perspectives 4: Action Theory and Philosophy of Mind"}, {"key": "8_CR22", "doi-asserted-by": "publisher", "first-page": "249", "DOI": "10.1111/1468-0068.00370", "volume": "36", "author": "E Schwitzgebel", "year": "2002", "unstructured": "Schwitzgebel, E. 2002, \u201cA Phenomenal, Dispositional Account of Belief\u201d, No\u00fbs 36, 249\u2013275.", "journal-title": "No\u00fbs"}, {"key": "8_CR23", "first-page": "41", "volume": "35", "author": "E Schwitzgebel", "year": "2011", "unstructured": "\u2014. 2011, \u201cKnowing Your Own Beliefs\u201d, Canadian Journal of Philosophy 35, 41\u201362.", "journal-title": "Canadian Journal of Philosophy"}, {"key": "8_CR24", "doi-asserted-by": "publisher", "first-page": "249", "DOI": "10.2307/2108488", "volume": "54", "author": "S Shoemaker", "year": "1994", "unstructured": "Shoemaker, S. 1994, \u201cSelf-knowledge and \u2018Inner Sense\u2019\u201d, Philosophy and Phenomenological Research 54, 249\u2013314.", "journal-title": "Philosophy and Phenomenological Research"}, {"key": "8_CR25", "author": "K Stanovich", "year": "1999", "unstructured": "Stanovich, K. 1999, Who is Rational? Mahwah, NJ: Erlbaum Press.", "volume-title": "Who is Rational?", "DOI": "10.4324/9781410603432", "doi-asserted-by": "crossref"}, {"key": "8_CR26", "author": "K Stanovich", "year": "2009", "unstructured": "\u2014. 2009, What Intelligence Tests Miss, New Haven, CT: Yale University Press.", "volume-title": "What Intelligence Tests Miss"}, {"key": "8_CR27", "author": "R Varley", "year": "1998", "unstructured": "Varley, R. 1998. \u201cAphasic Language, Aphasic Thought\u201d, in, P. and Boucher, J. (eds), Language and Thought, New York: Cambridge University Press.", "volume-title": "Language and Thought"}, {"key": "8_CR28", "author": "R Varley", "year": "2002", "unstructured": "\u2014. (2002). \u201cScience without Grammar: Scientific Reasoning in Severe Agrammatic Aphasia\u201d, in Carruthers, P., Laurence, S., and Stich, S. (eds), The Cognitive Basis of Science, New York: Oxford University Press.", "volume-title": "The Cognitive Basis of Science"}], "container-title": ["New Essays on Belief"], "link": [{"URL": "http://link.springer.com/content/pdf/10.1057/9781137026521_8", "content-type": "unspecified", "content-version": "vor", "intended-application": "similarity-checking"}], "deposited": {"date-parts": [[2019, 5, 7]], "date-time": "2019-05-07T01:46:13Z", "timestamp": 1557193573000}, "score": 28.277111, "issued": {"date-parts": [[2013]]}, "ISBN": ["9781349439225", "9781137026521"], "references-count": 28, "URL": "http://dx.doi.org/10.1057/9781137026521_8", "relation": {"cites": []}}